ics_vtimezones/__config__.py
ics_vtimezones/__init__.py
ics_vtimezones/data/windows_zone_mapping.json
ics_vtimezones/data/zoneinfo/Africa/Abidjan.ics
ics_vtimezones/data/zoneinfo/Africa/Accra.ics
ics_vtimezones/data/zoneinfo/Africa/Algiers.ics
ics_vtimezones/data/zoneinfo/Africa/Bissau.ics
ics_vtimezones/data/zoneinfo/Africa/Cairo.ics
ics_vtimezones/data/zoneinfo/Africa/Casablanca.ics
ics_vtimezones/data/zoneinfo/Africa/Ceuta.ics
ics_vtimezones/data/zoneinfo/Africa/El_Aaiun.ics
ics_vtimezones/data/zoneinfo/Africa/Johannesburg.ics
ics_vtimezones/data/zoneinfo/Africa/Juba.ics
ics_vtimezones/data/zoneinfo/Africa/Khartoum.ics
ics_vtimezones/data/zoneinfo/Africa/Lagos.ics
ics_vtimezones/data/zoneinfo/Africa/Maputo.ics
ics_vtimezones/data/zoneinfo/Africa/Monrovia.ics
ics_vtimezones/data/zoneinfo/Africa/Nairobi.ics
ics_vtimezones/data/zoneinfo/Africa/Ndjamena.ics
ics_vtimezones/data/zoneinfo/Africa/Sao_Tome.ics
ics_vtimezones/data/zoneinfo/Africa/Tripoli.ics
ics_vtimezones/data/zoneinfo/Africa/Tunis.ics
ics_vtimezones/data/zoneinfo/Africa/Windhoek.ics
ics_vtimezones/data/zoneinfo/America/Adak.ics
ics_vtimezones/data/zoneinfo/America/Anchorage.ics
ics_vtimezones/data/zoneinfo/America/Araguaina.ics
ics_vtimezones/data/zoneinfo/America/Argentina/Buenos_Aires.ics
ics_vtimezones/data/zoneinfo/America/Argentina/Catamarca.ics
ics_vtimezones/data/zoneinfo/America/Argentina/Cordoba.ics
ics_vtimezones/data/zoneinfo/America/Argentina/Jujuy.ics
ics_vtimezones/data/zoneinfo/America/Argentina/La_Rioja.ics
ics_vtimezones/data/zoneinfo/America/Argentina/Mendoza.ics
ics_vtimezones/data/zoneinfo/America/Argentina/Rio_Gallegos.ics
ics_vtimezones/data/zoneinfo/America/Argentina/Salta.ics
ics_vtimezones/data/zoneinfo/America/Argentina/San_Juan.ics
ics_vtimezones/data/zoneinfo/America/Argentina/San_Luis.ics
ics_vtimezones/data/zoneinfo/America/Argentina/Tucuman.ics
ics_vtimezones/data/zoneinfo/America/Argentina/Ushuaia.ics
ics_vtimezones/data/zoneinfo/America/Asuncion.ics
ics_vtimezones-2020.2.dist-info/METADATA
ics_vtimezones-2020.2.dist-info/WHEEL
ics_vtimezones-2020.2.dist-info/RECORD
