Metadata-Version: 2.1
Name: ics_vtimezones
Version: 2020.2
Summary: iCalendar vTimezone Data
Home-page: https://pypi.org/project/ics_vtimezones/
License: CC0-1.0
Keywords: ics,icalendar,rfc5545,timezone,vtimezone
Author: Niko Fink
Author-email: icspy@niko.fink.bayern
Requires-Python: >=3.7,<4.0
Classifier: License :: CC0 1.0 Universal (CC0 1.0) Public Domain Dedication
Classifier: Programming Language :: Python :: 3
Classifier: Programming Language :: Python :: 3.7
Classifier: Programming Language :: Python :: 3.8
Classifier: Programming Language :: Python :: 3.9
Classifier: Programming Language :: Python :: 3.10
Classifier: Programming Language :: Python :: 3.11
Classifier: Programming Language :: Python :: 3.12
Provides-Extra: update
Requires-Dist: ics (==0.8.*) ; extra == "update"
Requires-Dist: importlib_resources (>=1.4)
Project-URL: Documentation, https://icspy.readthedocs.io/en/stable/
Project-URL: Repository, https://github.com/N-Coder/ics_vtimezones
